[
    {
        "id": "lord_eliwood",
        "name": "Lord",
        "type": "unpromoted",
        "baseStats": {
            "hp": 18,
            "str": 5,
            "skl": 5,
            "spd": 7,
            "def": 5,
            "res": 0,
            "con": 7,
            "mov": 5
        },
        "promotionBonus": {},
        "promotesTo": [
            "knight_lord"
        ],
        "classAbilities": [],
        "weapons": [
            "Sword"
        ],
        "maxStats": {
            "hp": 60,
            "str": 20,
            "skl": 20,
            "spd": 20,
            "def": 20,
            "res": 20,
            "con": 20,
            "mov": 15,
            "lck": 30
        },
        "gender": "M",
        "movementType": "Infantry"
    },
    {
        "id": "lord_hector",
        "name": "Lord",
        "type": "unpromoted",
        "baseStats": {
            "hp": 19,
            "str": 7,
            "skl": 4,
            "spd": 5,
            "def": 8,
            "res": 0,
            "con": 13,
            "mov": 5
        },
        "promotionBonus": {},
        "promotesTo": [
            "great_lord"
        ],
        "classAbilities": [],
        "weapons": [
            "Axe"
        ],
        "maxStats": {
            "hp": 60,
            "str": 20,
            "skl": 20,
            "spd": 20,
            "def": 20,
            "res": 20,
            "con": 20,
            "mov": 15,
            "lck": 30
        },
        "gender": "M",
        "movementType": "Infantry"
    },
    {
        "id": "lord_lyn",
        "name": "Lord",
        "type": "unpromoted",
        "baseStats": {
            "hp": 16,
            "str": 4,
            "skl": 7,
            "spd": 9,
            "def": 2,
            "res": 0,
            "con": 5,
            "mov": 5
        },
        "promotionBonus": {},
        "promotesTo": [
            "blade_lord"
        ],
        "classAbilities": [],
        "weapons": [
            "Sword"
        ],
        "maxStats": {
            "hp": 60,
            "str": 20,
            "skl": 20,
            "spd": 20,
            "def": 20,
            "res": 20,
            "con": 20,
            "mov": 15,
            "lck": 30
        },
        "gender": "F",
        "movementType": "Infantry"
    },
    {
        "id": "cavalier_m",
        "name": "Cavalier",
        "type": "unpromoted",
        "baseStats": {
            "hp": 20,
            "str": 5,
            "skl": 2,
            "spd": 5,
            "def": 6,
            "res": 0,
            "con": 9,
            "mov": 7
        },
        "promotionBonus": {},
        "promotesTo": [
            "paladin_m"
        ],
        "classAbilities": [
            "Canto"
        ],
        "weapons": [
            "Swords",
            "Lances"
        ],
        "maxStats": {
            "hp": 60,
            "str": 20,
            "skl": 20,
            "spd": 20,
            "def": 20,
            "res": 20,
            "con": 20,
            "mov": 15,
            "lck": 30
        },
        "gender": "M",
        "movementType": "Cavalry"
    },
    {
        "id": "cavalier_f",
        "name": "Cavalier",
        "type": "unpromoted",
        "baseStats": {
            "hp": 18,
            "str": 5,
            "skl": 3,
            "spd": 3,
            "def": 6,
            "res": 0,
            "con": 9,
            "mov": 7
        },
        "promotionBonus": {},
        "promotesTo": [
            "paladin_f"
        ],
        "classAbilities": [
            "Canto"
        ],
        "weapons": [
            "Swords",
            "Lances"
        ],
        "maxStats": {
            "hp": 60,
            "str": 20,
            "skl": 20,
            "spd": 20,
            "def": 20,
            "res": 20,
            "con": 20,
            "mov": 15,
            "lck": 30
        },
        "gender": "F",
        "movementType": "Cavalry"
    },
    {
        "id": "knight_m",
        "name": "Knight",
        "type": "unpromoted",
        "baseStats": {
            "hp": 17,
            "str": 5,
            "skl": 2,
            "spd": 0,
            "def": 9,
            "res": 0,
            "con": 13,
            "mov": 4
        },
        "promotionBonus": {},
        "promotesTo": [
            "general_m"
        ],
        "classAbilities": [],
        "weapons": [
            "Lances"
        ],
        "maxStats": {
            "hp": 60,
            "str": 20,
            "skl": 20,
            "spd": 20,
            "def": 20,
            "res": 20,
            "con": 20,
            "mov": 15,
            "lck": 30
        },
        "gender": "M",
        "movementType": "Armored"
    },
    {
        "id": "knight_f",
        "name": "Knight",
        "type": "unpromoted",
        "baseStats": {
            "hp": 16,
            "str": 4,
            "skl": 3,
            "spd": 1,
            "def": 8,
            "res": 1,
            "con": 10,
            "mov": 4
        },
        "promotionBonus": {},
        "promotesTo": [
            "general_f"
        ],
        "classAbilities": [],
        "weapons": [
            "Lances"
        ],
        "maxStats": {
            "hp": 60,
            "str": 20,
            "skl": 20,
            "spd": 20,
            "def": 20,
            "res": 20,
            "con": 20,
            "mov": 15,
            "lck": 30
        },
        "gender": "F",
        "movementType": "Armored"
    },
    {
        "id": "thief_m",
        "name": "Thief",
        "type": "unpromoted",
        "baseStats": {
            "hp": 16,
            "str": 3,
            "skl": 1,
            "spd": 9,
            "def": 2,
            "res": 0,
            "con": 6,
            "mov": 6
        },
        "promotionBonus": {},
        "promotesTo": [
            "assassin"
        ],
        "classAbilities": [
            "Lockpick",
            "Steal"
        ],
        "weapons": [
            "Swords"
        ],
        "maxStats": {
            "hp": 60,
            "str": 20,
            "skl": 20,
            "spd": 20,
            "def": 20,
            "res": 20,
            "con": 20,
            "mov": 15,
            "lck": 30
        },
        "gender": "M",
        "movementType": "Infantry"
    },
    {
        "id": "thief_f",
        "name": "Thief",
        "type": "unpromoted",
        "baseStats": {
            "hp": 15,
            "str": 2,
            "skl": 3,
            "spd": 8,
            "def": 1,
            "res": 2,
            "con": 5,
            "mov": 6
        },
        "promotionBonus": {},
        "promotesTo": [
            "assassin"
        ],
        "classAbilities": [
            "Lockpick",
            "Steal"
        ],
        "weapons": [
            "Swords"
        ],
        "maxStats": {
            "hp": 60,
            "str": 20,
            "skl": 20,
            "spd": 20,
            "def": 20,
            "res": 20,
            "con": 20,
            "mov": 15,
            "lck": 30
        },
        "gender": "F",
        "movementType": "Infantry"
    },
    {
        "id": "mercenary_m",
        "name": "Mercenary",
        "type": "unpromoted",
        "baseStats": {
            "hp": 18,
            "str": 4,
            "skl": 8,
            "spd": 8,
            "def": 4,
            "res": 0,
            "con": 9,
            "mov": 5
        },
        "promotionBonus": {},
        "promotesTo": [
            "hero_m"
        ],
        "classAbilities": [],
        "weapons": [
            "Swords"
        ],
        "maxStats": {
            "hp": 60,
            "str": 20,
            "skl": 20,
            "spd": 20,
            "def": 20,
            "res": 20,
            "con": 20,
            "mov": 15,
            "lck": 30
        },
        "gender": "M",
        "movementType": "Infantry"
    },
    {
        "id": "mercenary_f",
        "name": "Mercenary",
        "type": "unpromoted",
        "baseStats": {
            "hp": 16,
            "str": 3,
            "skl": 5,
            "spd": 6,
            "def": 2,
            "res": 0,
            "con": 8,
            "mov": 5
        },
        "promotionBonus": {},
        "promotesTo": [
            "hero_f"
        ],
        "classAbilities": [],
        "weapons": [
            "Swords"
        ],
        "maxStats": {
            "hp": 60,
            "str": 20,
            "skl": 20,
            "spd": 20,
            "def": 20,
            "res": 20,
            "con": 20,
            "mov": 15,
            "lck": 30
        },
        "gender": "F",
        "movementType": "Infantry"
    },
    {
        "id": "myrmidon_m",
        "name": "Myrmidon",
        "type": "unpromoted",
        "baseStats": {
            "hp": 16,
            "str": 4,
            "skl": 9,
            "spd": 9,
            "def": 2,
            "res": 0,
            "con": 8,
            "mov": 5
        },
        "promotionBonus": {},
        "promotesTo": [
            "swordmaster_m"
        ],
        "classAbilities": [],
        "weapons": [
            "Swords"
        ],
        "maxStats": {
            "hp": 60,
            "str": 20,
            "skl": 20,
            "spd": 20,
            "def": 20,
            "res": 20,
            "con": 20,
            "mov": 15,
            "lck": 30
        },
        "gender": "M",
        "movementType": "Infantry"
    },
    {
        "id": "myrmidon_f",
        "name": "Myrmidon",
        "type": "unpromoted",
        "baseStats": {
            "hp": 15,
            "str": 3,
            "skl": 9,
            "spd": 10,
            "def": 1,
            "res": 1,
            "con": 5,
            "mov": 5
        },
        "promotionBonus": {},
        "promotesTo": [
            "swordmaster_f"
        ],
        "classAbilities": [],
        "weapons": [
            "Swords"
        ],
        "maxStats": {
            "hp": 60,
            "str": 20,
            "skl": 20,
            "spd": 20,
            "def": 20,
            "res": 20,
            "con": 20,
            "mov": 15,
            "lck": 30
        },
        "gender": "F",
        "movementType": "Infantry"
    },
    {
        "id": "archer_m",
        "name": "Archer",
        "type": "unpromoted",
        "baseStats": {
            "hp": 18,
            "str": 4,
            "skl": 3,
            "spd": 3,
            "def": 3,
            "res": 0,
            "con": 7,
            "mov": 5
        },
        "promotionBonus": {},
        "promotesTo": [
            "sniper_m"
        ],
        "classAbilities": [],
        "weapons": [
            "Bows"
        ],
        "maxStats": {
            "hp": 60,
            "str": 20,
            "skl": 20,
            "spd": 20,
            "def": 20,
            "res": 20,
            "con": 20,
            "mov": 15,
            "lck": 30
        },
        "gender": "M",
        "movementType": "Infantry"
    },
    {
        "id": "archer_f",
        "name": "Archer",
        "type": "unpromoted",
        "baseStats": {
            "hp": 17,
            "str": 3,
            "skl": 3,
            "spd": 4,
            "def": 3,
            "res": 0,
            "con": 5,
            "mov": 5
        },
        "promotionBonus": {},
        "promotesTo": [
            "sniper_f"
        ],
        "classAbilities": [],
        "weapons": [
            "Bows"
        ],
        "maxStats": {
            "hp": 60,
            "str": 20,
            "skl": 20,
            "spd": 20,
            "def": 20,
            "res": 20,
            "con": 20,
            "mov": 15,
            "lck": 30
        },
        "gender": "F",
        "movementType": "Infantry"
    },
    {
        "id": "nomad_m",
        "name": "Nomad",
        "type": "unpromoted",
        "baseStats": {
            "hp": 16,
            "str": 5,
            "skl": 4,
            "spd": 5,
            "def": 4,
            "res": 0,
            "con": 7,
            "mov": 7
        },
        "promotionBonus": {},
        "promotesTo": [
            "nomadic_trooper_m"
        ],
        "classAbilities": [
            "Canto"
        ],
        "weapons": [
            "Bows"
        ],
        "maxStats": {
            "hp": 60,
            "str": 20,
            "skl": 20,
            "spd": 20,
            "def": 20,
            "res": 20,
            "con": 20,
            "mov": 15,
            "lck": 30
        },
        "gender": "M",
        "movementType": "Cavalry"
    },
    {
        "id": "nomad_f",
        "name": "Nomad",
        "type": "unpromoted",
        "baseStats": {
            "hp": 15,
            "str": 4,
            "skl": 5,
            "spd": 6,
            "def": 3,
            "res": 0,
            "con": 5,
            "mov": 7
        },
        "promotionBonus": {},
        "promotesTo": [
            "nomadic_trooper_f"
        ],
        "classAbilities": [
            "Canto"
        ],
        "weapons": [
            "Bows"
        ],
        "maxStats": {
            "hp": 60,
            "str": 20,
            "skl": 20,
            "spd": 20,
            "def": 20,
            "res": 20,
            "con": 20,
            "mov": 15,
            "lck": 30
        },
        "gender": "F",
        "movementType": "Cavalry"
    },
    {
        "id": "fighter",
        "name": "Fighter",
        "type": "unpromoted",
        "baseStats": {
            "hp": 20,
            "str": 5,
            "skl": 2,
            "spd": 4,
            "def": 2,
            "res": 0,
            "con": 11,
            "mov": 5
        },
        "promotionBonus": {},
        "promotesTo": [
            "warrior"
        ],
        "classAbilities": [],
        "weapons": [
            "Axes"
        ],
        "maxStats": {
            "hp": 60,
            "str": 20,
            "skl": 20,
            "spd": 20,
            "def": 20,
            "res": 20,
            "con": 20,
            "mov": 15,
            "lck": 30
        },
        "gender": "M",
        "movementType": "Infantry"
    },
    {
        "id": "brigand",
        "name": "Brigand",
        "type": "unpromoted",
        "baseStats": {
            "hp": 20,
            "str": 5,
            "skl": 1,
            "spd": 5,
            "def": 3,
            "res": 0,
            "con": 12,
            "mov": 5
        },
        "promotionBonus": {},
        "promotesTo": [
            "assassin"
        ],
        "classAbilities": [
            "Mountain Walk"
        ],
        "weapons": [
            "Swords"
        ],
        "maxStats": {
            "hp": 60,
            "str": 20,
            "skl": 20,
            "spd": 20,
            "def": 20,
            "res": 20,
            "con": 20,
            "mov": 15,
            "lck": 30
        },
        "gender": "M",
        "movementType": "Infantry"
    },
    {
        "id": "pirate",
        "name": "Pirate",
        "type": "unpromoted",
        "baseStats": {
            "hp": 19,
            "str": 4,
            "skl": 2,
            "spd": 6,
            "def": 3,
            "res": 0,
            "con": 10,
            "mov": 5
        },
        "promotionBonus": {},
        "promotesTo": [
            "berserker"
        ],
        "classAbilities": [
            "Water Walk"
        ],
        "weapons": [
            "Axes"
        ],
        "maxStats": {
            "hp": 60,
            "str": 20,
            "skl": 20,
            "spd": 20,
            "def": 20,
            "res": 20,
            "con": 20,
            "mov": 15,
            "lck": 30
        },
        "gender": "M",
        "movementType": "Infantry"
    },
    {
        "id": "corsair",
        "name": "Corsair",
        "type": "unpromoted",
        "baseStats": {
            "hp": 19,
            "str": 4,
            "skl": 2,
            "spd": 6,
            "def": 3,
            "res": 0,
            "con": 10,
            "mov": 5
        },
        "promotionBonus": {},
        "promotesTo": [
            "berserker"
        ],
        "classAbilities": [
            "Water Walk"
        ],
        "weapons": [
            "Axes"
        ],
        "maxStats": {
            "hp": 60,
            "str": 20,
            "skl": 20,
            "spd": 20,
            "def": 20,
            "res": 20,
            "con": 20,
            "mov": 15,
            "lck": 30
        },
        "gender": "M",
        "movementType": "Infantry"
    },
    {
        "id": "pegasus_knight",
        "name": "Pegasus Knight",
        "type": "unpromoted",
        "baseStats": {
            "hp": 14,
            "str": 4,
            "skl": 5,
            "spd": 5,
            "def": 3,
            "res": 2,
            "con": 5,
            "mov": 7
        },
        "promotionBonus": {},
        "promotesTo": [
            "falcon_knight"
        ],
        "classAbilities": [
            "Canto"
        ],
        "weapons": [
            "Lances"
        ],
        "maxStats": {
            "hp": 60,
            "str": 20,
            "skl": 20,
            "spd": 20,
            "def": 20,
            "res": 20,
            "con": 20,
            "mov": 15,
            "lck": 30
        },
        "gender": "F",
        "movementType": "Flying"
    },
    {
        "id": "wyvern_rider_m",
        "name": "Wyvern Rider",
        "type": "unpromoted",
        "baseStats": {
            "hp": 20,
            "str": 7,
            "skl": 3,
            "spd": 5,
            "def": 8,
            "res": 0,
            "con": 10,
            "mov": 7
        },
        "promotionBonus": {},
        "promotesTo": [
            "wyvern_lord_m"
        ],
        "classAbilities": [
            "Canto"
        ],
        "weapons": [
            "Lances"
        ],
        "maxStats": {
            "hp": 60,
            "str": 20,
            "skl": 20,
            "spd": 20,
            "def": 20,
            "res": 20,
            "con": 20,
            "mov": 15,
            "lck": 30
        },
        "gender": "M",
        "movementType": "Wyvern"
    },
    {
        "id": "wyvern_rider_f",
        "name": "Wyvern Rider",
        "type": "unpromoted",
        "baseStats": {
            "hp": 19,
            "str": 6,
            "skl": 5,
            "spd": 5,
            "def": 7,
            "res": 0,
            "con": 9,
            "mov": 7
        },
        "promotionBonus": {},
        "promotesTo": [
            "wyvern_lord_f"
        ],
        "classAbilities": [
            "Canto"
        ],
        "weapons": [
            "Lances"
        ],
        "maxStats": {
            "hp": 60,
            "str": 20,
            "skl": 20,
            "spd": 20,
            "def": 20,
            "res": 20,
            "con": 20,
            "mov": 15,
            "lck": 30
        },
        "gender": "F",
        "movementType": "Wyvern"
    },
    {
        "id": "mage_m",
        "name": "Mage",
        "type": "unpromoted",
        "baseStats": {
            "hp": 16,
            "str": 1,
            "skl": 2,
            "spd": 3,
            "def": 3,
            "res": 3,
            "con": 6,
            "mov": 5
        },
        "promotionBonus": {},
        "promotesTo": [
            "sage_m"
        ],
        "classAbilities": [],
        "weapons": [
            "Anima"
        ],
        "maxStats": {
            "hp": 60,
            "str": 20,
            "skl": 20,
            "spd": 20,
            "def": 20,
            "res": 20,
            "con": 20,
            "mov": 15,
            "lck": 30
        },
        "gender": "M",
        "movementType": "Infantry"
    },
    {
        "id": "mage_f",
        "name": "Mage",
        "type": "unpromoted",
        "baseStats": {
            "hp": 16,
            "str": 1,
            "skl": 3,
            "spd": 2,
            "def": 2,
            "res": 4,
            "con": 3,
            "mov": 5
        },
        "promotionBonus": {},
        "promotesTo": [
            "sage_f"
        ],
        "classAbilities": [],
        "weapons": [
            "Anima"
        ],
        "maxStats": {
            "hp": 60,
            "str": 20,
            "skl": 20,
            "spd": 20,
            "def": 20,
            "res": 20,
            "con": 20,
            "mov": 15,
            "lck": 30
        },
        "gender": "F",
        "movementType": "Infantry"
    },
    {
        "id": "monk",
        "name": "Monk",
        "type": "unpromoted",
        "baseStats": {
            "hp": 18,
            "str": 1,
            "skl": 1,
            "spd": 2,
            "def": 1,
            "res": 5,
            "con": 6,
            "mov": 5
        },
        "promotionBonus": {},
        "promotesTo": [
            "bishop_m"
        ],
        "classAbilities": [],
        "weapons": [
            "Light"
        ],
        "maxStats": {
            "hp": 60,
            "str": 20,
            "skl": 20,
            "spd": 20,
            "def": 20,
            "res": 20,
            "con": 20,
            "mov": 15,
            "lck": 30
        },
        "gender": "M",
        "movementType": "Infantry"
    },
    {
        "id": "cleric",
        "name": "Cleric",
        "type": "unpromoted",
        "baseStats": {
            "hp": 16,
            "str": 1,
            "skl": 2,
            "spd": 2,
            "def": 0,
            "res": 6,
            "con": 4,
            "mov": 5
        },
        "promotionBonus": {},
        "promotesTo": [
            "bishop_f"
        ],
        "classAbilities": [],
        "weapons": [
            "Staves"
        ],
        "maxStats": {
            "hp": 60,
            "str": 20,
            "skl": 20,
            "spd": 20,
            "def": 20,
            "res": 20,
            "con": 20,
            "mov": 15,
            "lck": 30
        },
        "gender": "F",
        "movementType": "Infantry"
    },
    {
        "id": "shaman_m",
        "name": "Shaman",
        "type": "unpromoted",
        "baseStats": {
            "hp": 16,
            "str": 2,
            "skl": 1,
            "spd": 2,
            "def": 2,
            "res": 4,
            "con": 7,
            "mov": 5
        },
        "promotionBonus": {},
        "promotesTo": [
            "druid_m"
        ],
        "classAbilities": [],
        "weapons": [
            "Dark"
        ],
        "maxStats": {
            "hp": 60,
            "str": 20,
            "skl": 20,
            "spd": 20,
            "def": 20,
            "res": 20,
            "con": 20,
            "mov": 15,
            "lck": 30
        },
        "gender": "M",
        "movementType": "Infantry"
    },
    {
        "id": "shaman_f",
        "name": "Shaman",
        "type": "unpromoted",
        "baseStats": {
            "hp": 15,
            "str": 3,
            "skl": 1,
            "spd": 1,
            "def": 1,
            "res": 5,
            "con": 3,
            "mov": 5
        },
        "promotionBonus": {},
        "promotesTo": [
            "druid_f"
        ],
        "classAbilities": [],
        "weapons": [
            "Dark"
        ],
        "maxStats": {
            "hp": 60,
            "str": 20,
            "skl": 20,
            "spd": 20,
            "def": 20,
            "res": 20,
            "con": 20,
            "mov": 15,
            "lck": 30
        },
        "gender": "F",
        "movementType": "Infantry"
    },
    {
        "id": "troubadour",
        "name": "Troubadour",
        "type": "unpromoted",
        "baseStats": {
            "hp": 15,
            "str": 1,
            "skl": 1,
            "spd": 3,
            "def": 2,
            "res": 5,
            "con": 5,
            "mov": 7
        },
        "promotionBonus": {},
        "promotesTo": [
            "valkyrie"
        ],
        "classAbilities": [
            "Canto"
        ],
        "weapons": [
            "Staves"
        ],
        "maxStats": {
            "hp": 60,
            "str": 20,
            "skl": 20,
            "spd": 20,
            "def": 20,
            "res": 20,
            "con": 20,
            "mov": 15,
            "lck": 30
        },
        "gender": "F",
        "movementType": "Cavalry"
    },
    {
        "id": "soldier",
        "name": "Soldier",
        "type": "unpromoted",
        "baseStats": {
            "hp": 20,
            "str": 3,
            "skl": 0,
            "spd": 1,
            "def": 0,
            "res": 0,
            "con": 6,
            "mov": 5
        },
        "promotionBonus": {},
        "promotesTo": [],
        "classAbilities": [
            "+15 Crit"
        ],
        "weapons": [
            "Bow"
        ],
        "maxStats": {
            "hp": 60,
            "str": 20,
            "skl": 20,
            "spd": 20,
            "def": 20,
            "res": 20,
            "con": 20,
            "mov": 15,
            "lck": 30
        },
        "gender": "M",
        "movementType": "Infantry"
    },
    {
        "id": "dancer",
        "name": "Dancer",
        "type": "unpromoted",
        "baseStats": {
            "hp": 14,
            "str": 1,
            "skl": 2,
            "spd": 7,
            "def": 0,
            "res": 1,
            "con": 4,
            "mov": 5
        },
        "promotionBonus": {},
        "promotesTo": [],
        "classAbilities": [
            "Dance"
        ],
        "weapons": [],
        "maxStats": {
            "hp": 60,
            "str": 20,
            "skl": 20,
            "spd": 20,
            "def": 20,
            "res": 20,
            "con": 20,
            "mov": 15,
            "lck": 30
        },
        "gender": "F",
        "movementType": "Infantry"
    },
    {
        "id": "bard",
        "name": "Bard",
        "type": "unpromoted",
        "baseStats": {
            "hp": 14,
            "str": 1,
            "skl": 2,
            "spd": 7,
            "def": 1,
            "res": 0,
            "con": 3,
            "mov": 5
        },
        "promotionBonus": {},
        "promotesTo": [],
        "classAbilities": [
            "Play"
        ],
        "weapons": [],
        "maxStats": {
            "hp": 60,
            "str": 20,
            "skl": 20,
            "spd": 20,
            "def": 20,
            "res": 20,
            "con": 20,
            "mov": 15,
            "lck": 30
        },
        "gender": "M",
        "movementType": "Infantry"
    },
    {
        "id": "knight_lord",
        "name": "Knight Lord",
        "type": "promoted",
        "baseStats": {
            "hp": 18,
            "str": 3,
            "skl": 3,
            "spd": 4,
            "def": 5,
            "res": 0,
            "con": 9,
            "mov": 7
        },
        "promotionBonus": {
            "hp": 4,
            "str": 2,
            "skl": 0,
            "spd": 1,
            "def": 1,
            "res": 3,
            "con": 2,
            "mov": 2
        },
        "promotesTo": [],
        "classAbilities": [
            "Canto"
        ],
        "weapons": [
            "Sword",
            "Lance"
        ],
        "maxStats": {
            "hp": 60,
            "str": 27,
            "skl": 26,
            "spd": 24,
            "def": 23,
            "res": 25,
            "con": 25,
            "mov": 15,
            "lck": 30
        },
        "gender": "M",
        "movementType": "Cavalry"
    },
    {
        "id": "great_lord",
        "name": "Great Lord",
        "type": "promoted",
        "baseStats": {
            "hp": 18,
            "str": 3,
            "skl": 3,
            "spd": 4,
            "def": 5,
            "res": 0,
            "con": 15,
            "mov": 5
        },
        "promotionBonus": {
            "hp": 3,
            "str": 0,
            "skl": 2,
            "spd": 3,
            "def": 1,
            "res": 5,
            "con": 2,
            "mov": 0
        },
        "promotesTo": [],
        "classAbilities": [],
        "weapons": [
            "Axe",
            "Sword"
        ],
        "maxStats": {
            "hp": 60,
            "str": 30,
            "skl": 24,
            "spd": 24,
            "def": 29,
            "res": 20,
            "con": 25,
            "mov": 15,
            "lck": 30
        },
        "gender": "M",
        "movementType": "Infantry"
    },
    {
        "id": "blade_lord",
        "name": "Blade Lord",
        "type": "promoted",
        "baseStats": {
            "hp": 18,
            "str": 3,
            "skl": 3,
            "spd": 4,
            "def": 5,
            "res": 0,
            "con": 6,
            "mov": 6
        },
        "promotionBonus": {
            "hp": 3,
            "str": 2,
            "skl": 2,
            "spd": 0,
            "def": 3,
            "res": 5,
            "con": 1,
            "mov": 1
        },
        "promotesTo": [],
        "classAbilities": [
            "+15 Crit"
        ],
        "weapons": [
            "Bow"
        ],
        "maxStats": {
            "hp": 60,
            "str": 24,
            "skl": 29,
            "spd": 30,
            "def": 22,
            "res": 22,
            "con": 25,
            "mov": 15,
            "lck": 30
        },
        "gender": "F",
        "movementType": "Infantry"
    },
    {
        "id": "paladin_m",
        "name": "Paladin",
        "type": "promoted",
        "baseStats": {
            "hp": 23,
            "str": 7,
            "skl": 4,
            "spd": 7,
            "def": 8,
            "res": 3,
            "con": 11,
            "mov": 8
        },
        "promotionBonus": {
            "hp": 2,
            "str": 1,
            "skl": 1,
            "spd": 1,
            "def": 2,
            "res": 1,
            "con": 2,
            "mov": 1
        },
        "promotesTo": [],
        "classAbilities": [
            "Canto"
        ],
        "weapons": [
            "Sword",
            "Lance",
            "Axe"
        ],
        "maxStats": {
            "hp": 60,
            "str": 25,
            "skl": 26,
            "spd": 24,
            "def": 25,
            "res": 25,
            "con": 25,
            "mov": 15,
            "lck": 30
        },
        "gender": "M",
        "movementType": "Cavalry"
    },
    {
        "id": "paladin_f",
        "name": "Paladin",
        "type": "promoted",
        "baseStats": {
            "hp": 23,
            "str": 6,
            "skl": 6,
            "spd": 11,
            "def": 7,
            "res": 6,
            "con": 9,
            "mov": 8
        },
        "promotionBonus": {
            "hp": 2,
            "str": 1,
            "skl": 1,
            "spd": 1,
            "def": 2,
            "res": 1,
            "con": 2,
            "mov": 1
        },
        "promotesTo": [],
        "classAbilities": [
            "Canto"
        ],
        "weapons": [
            "Sword",
            "Lance",
            "Axe"
        ],
        "maxStats": {
            "hp": 60,
            "str": 23,
            "skl": 27,
            "spd": 25,
            "def": 24,
            "res": 26,
            "con": 25,
            "mov": 15,
            "lck": 30
        },
        "gender": "F",
        "movementType": "Cavalry"
    },
    {
        "id": "general_m",
        "name": "General",
        "type": "promoted",
        "baseStats": {
            "hp": 21,
            "str": 8,
            "skl": 4,
            "spd": 3,
            "def": 13,
            "res": 3,
            "con": 15,
            "mov": 5
        },
        "promotionBonus": {
            "hp": 4,
            "str": 2,
            "skl": 2,
            "spd": 3,
            "def": 2,
            "res": 3,
            "con": 2,
            "mov": 1
        },
        "promotesTo": [],
        "classAbilities": [],
        "weapons": [
            "Lance",
            "Axe"
        ],
        "maxStats": {
            "hp": 60,
            "str": 29,
            "skl": 27,
            "spd": 24,
            "def": 30,
            "res": 25,
            "con": 20,
            "mov": 15,
            "lck": 30
        },
        "gender": "M",
        "movementType": "Armored"
    },
    {
        "id": "general_f",
        "name": "General",
        "type": "promoted",
        "baseStats": {
            "hp": 20,
            "str": 8,
            "skl": 5,
            "spd": 5,
            "def": 11,
            "res": 4,
            "con": 11,
            "mov": 5
        },
        "promotionBonus": {
            "hp": 4,
            "str": 2,
            "skl": 2,
            "spd": 3,
            "def": 2,
            "res": 3,
            "con": 2,
            "mov": 1
        },
        "promotesTo": [],
        "classAbilities": [],
        "weapons": [
            "Lance",
            "Axe",
            "Sword"
        ],
        "maxStats": {
            "hp": 60,
            "str": 25,
            "skl": 25,
            "spd": 22,
            "def": 30,
            "res": 26,
            "con": 20,
            "mov": 15,
            "lck": 30
        },
        "gender": "F",
        "movementType": "Armored"
    },
    {
        "id": "hero_m",
        "name": "Hero",
        "type": "promoted",
        "baseStats": {
            "hp": 22,
            "str": 6,
            "skl": 9,
            "spd": 10,
            "def": 8,
            "res": 2,
            "con": 10,
            "mov": 6
        },
        "promotionBonus": {
            "hp": 4,
            "str": 0,
            "skl": 2,
            "spd": 2,
            "def": 2,
            "res": 2,
            "con": 1,
            "mov": 1
        },
        "promotesTo": [],
        "classAbilities": [
            "+15 Crit"
        ],
        "weapons": [
            "Bow"
        ],
        "maxStats": {
            "hp": 60,
            "str": 25,
            "skl": 30,
            "spd": 28,
            "def": 25,
            "res": 23,
            "con": 20,
            "mov": 15,
            "lck": 30
        },
        "gender": "M",
        "movementType": "Infantry"
    },
    {
        "id": "sniper_f",
        "name": "Sniper",
        "type": "promoted",
        "baseStats": {
            "hp": 19,
            "str": 6,
            "skl": 6,
            "spd": 7,
            "def": 5,
            "res": 3,
            "con": 6,
            "mov": 6
        },
        "promotionBonus": {
            "hp": 4,
            "str": 3,
            "skl": 1,
            "spd": 1,
            "def": 2,
            "res": 2,
            "con": 1,
            "mov": 1
        },
        "promotesTo": [],
        "classAbilities": [],
        "weapons": [
            "Bow"
        ],
        "maxStats": {
            "hp": 60,
            "str": 24,
            "skl": 30,
            "spd": 29,
            "def": 24,
            "res": 24,
            "con": 20,
            "mov": 15,
            "lck": 30
        },
        "gender": "F",
        "movementType": "Infantry"
    },
    {
        "id": "nomadic_trooper_m",
        "name": "Nomadic Trooper",
        "type": "promoted",
        "baseStats": {
            "hp": 21,
            "str": 7,
            "skl": 6,
            "spd": 7,
            "def": 6,
            "res": 3,
            "con": 8,
            "mov": 8
        },
        "promotionBonus": {
            "hp": 3,
            "str": 2,
            "skl": 1,
            "spd": 1,
            "def": 3,
            "res": 3,
            "con": 1,
            "mov": 1
        },
        "promotesTo": [],
        "classAbilities": [
            "Canto"
        ],
        "weapons": [
            "Bow",
            "Sword"
        ],
        "maxStats": {
            "hp": 60,
            "str": 25,
            "skl": 28,
            "spd": 30,
            "def": 24,
            "res": 23,
            "con": 20,
            "mov": 15,
            "lck": 30
        },
        "gender": "M",
        "movementType": "Cavalry"
    },
    {
        "id": "nomadic_trooper_f",
        "name": "Nomadic Trooper",
        "type": "promoted",
        "baseStats": {
            "hp": 21,
            "str": 6,
            "skl": 6,
            "spd": 7,
            "def": 5,
            "res": 4,
            "con": 6,
            "mov": 8
        },
        "promotionBonus": {
            "hp": 3,
            "str": 2,
            "skl": 1,
            "spd": 1,
            "def": 3,
            "res": 3,
            "con": 1,
            "mov": 1
        },
        "promotesTo": [],
        "classAbilities": [
            "Canto"
        ],
        "weapons": [
            "Bow",
            "Sword"
        ],
        "maxStats": {
            "hp": 60,
            "str": 23,
            "skl": 28,
            "spd": 30,
            "def": 22,
            "res": 25,
            "con": 20,
            "mov": 15,
            "lck": 30
        },
        "gender": "F",
        "movementType": "Cavalry"
    },
    {
        "id": "warrior",
        "name": "Warrior",
        "type": "promoted",
        "baseStats": {
            "hp": 28,
            "str": 8,
            "skl": 5,
            "spd": 6,
            "def": 5,
            "res": 0,
            "con": 13,
            "mov": 6
        },
        "promotionBonus": {
            "hp": 3,
            "str": 1,
            "skl": 2,
            "spd": 0,
            "def": 3,
            "res": 3,
            "con": 2,
            "mov": 1
        },
        "promotesTo": [],
        "classAbilities": [],
        "weapons": [
            "Axe",
            "Bow"
        ],
        "maxStats": {
            "hp": 60,
            "str": 30,
            "skl": 28,
            "spd": 26,
            "def": 26,
            "res": 22,
            "con": 20,
            "mov": 15,
            "lck": 30
        },
        "gender": "M",
        "movementType": "Infantry"
    },
    {
        "id": "berserker",
        "name": "Berserker",
        "type": "promoted",
        "baseStats": {
            "hp": 24,
            "str": 7,
            "skl": 6,
            "spd": 7,
            "def": 6,
            "res": 0,
            "con": 13,
            "mov": 6
        },
        "promotionBonus": {
            "hp": 4,
            "str": 1,
            "skl": 1,
            "spd": 1,
            "def": 2,
            "res": 2,
            "con": 3,
            "mov": 1
        },
        "promotesTo": [],
        "classAbilities": [
            "+15 Crit",
            "Water Walk"
        ],
        "weapons": [
            "Axe"
        ],
        "maxStats": {
            "hp": 60,
            "str": 30,
            "skl": 29,
            "spd": 28,
            "def": 23,
            "res": 21,
            "con": 20,
            "mov": 15,
            "lck": 30
        },
        "gender": "M",
        "movementType": "Infantry"
    },
    {
        "id": "falcon_knight",
        "name": "Falcon Knight",
        "type": "promoted",
        "baseStats": {
            "hp": 20,
            "str": 6,
            "skl": 7,
            "spd": 7,
            "def": 5,
            "res": 4,
            "con": 6,
            "mov": 8
        },
        "promotionBonus": {
            "hp": 5,
            "str": 2,
            "skl": 0,
            "spd": 0,
            "def": 2,
            "res": 2,
            "con": 1,
            "mov": 1
        },
        "promotesTo": [],
        "classAbilities": [
            "Canto"
        ],
        "weapons": [
            "Lance",
            "Sword"
        ],
        "maxStats": {
            "hp": 60,
            "str": 23,
            "skl": 25,
            "spd": 28,
            "def": 23,
            "res": 26,
            "con": 25,
            "mov": 15,
            "lck": 30
        },
        "gender": "F",
        "movementType": "Flying"
    },
    {
        "id": "wyvern_lord_m",
        "name": "Wyvern Lord",
        "type": "promoted",
        "baseStats": {
            "hp": 25,
            "str": 9,
            "skl": 5,
            "spd": 7,
            "def": 10,
            "res": 1,
            "con": 11,
            "mov": 8
        },
        "promotionBonus": {
            "hp": 4,
            "str": 0,
            "skl": 2,
            "spd": 2,
            "def": 0,
            "res": 2,
            "con": 1,
            "mov": 1
        },
        "promotesTo": [],
        "classAbilities": [
            "Canto"
        ],
        "weapons": [
            "Lance",
            "Sword"
        ],
        "maxStats": {
            "hp": 60,
            "str": 27,
            "skl": 25,
            "spd": 23,
            "def": 28,
            "res": 22,
            "con": 25,
            "mov": 15,
            "lck": 30
        },
        "gender": "M",
        "movementType": "Wyvern"
    },
    {
        "id": "wyvern_lord_f",
        "name": "Wyvern Lord",
        "type": "promoted",
        "baseStats": {
            "hp": 24,
            "str": 8,
            "skl": 7,
            "spd": 7,
            "def": 9,
            "res": 2,
            "con": 10,
            "mov": 8
        },
        "promotionBonus": {
            "hp": 4,
            "str": 0,
            "skl": 2,
            "spd": 2,
            "def": 0,
            "res": 2,
            "con": 1,
            "mov": 1
        },
        "promotesTo": [],
        "classAbilities": [
            "Canto"
        ],
        "weapons": [
            "Lance",
            "Sword"
        ],
        "maxStats": {
            "hp": 60,
            "str": 25,
            "skl": 26,
            "spd": 24,
            "def": 27,
            "res": 23,
            "con": 25,
            "mov": 15,
            "lck": 30
        },
        "gender": "F",
        "movementType": "Wyvern"
    },
    {
        "id": "sage_m",
        "name": "Sage",
        "type": "promoted",
        "baseStats": {
            "hp": 20,
            "str": 5,
            "skl": 4,
            "spd": 4,
            "def": 5,
            "res": 5,
            "con": 7,
            "mov": 6
        },
        "promotionBonus": {
            "hp": 4,
            "str": 1,
            "skl": 0,
            "spd": 0,
            "def": 3,
            "res": 3,
            "con": 1,
            "mov": 1
        },
        "promotesTo": [],
        "classAbilities": [],
        "weapons": [
            "Anima",
            "Staff"
        ],
        "maxStats": {
            "hp": 60,
            "str": 28,
            "skl": 30,
            "spd": 26,
            "def": 21,
            "res": 25,
            "con": 20,
            "mov": 15,
            "lck": 30
        },
        "gender": "M",
        "movementType": "Infantry"
    },
    {
        "id": "sage_f",
        "name": "Sage",
        "type": "promoted",
        "baseStats": {
            "hp": 19,
            "str": 4,
            "skl": 6,
            "spd": 5,
            "def": 3,
            "res": 6,
            "con": 4,
            "mov": 6
        },
        "promotionBonus": {
            "hp": 3,
            "str": 1,
            "skl": 1,
            "spd": 0,
            "def": 3,
            "res": 3,
            "con": 1,
            "mov": 1
        },
        "promotesTo": [],
        "classAbilities": [],
        "weapons": [
            "Anima",
            "Staff"
        ],
        "maxStats": {
            "hp": 60,
            "str": 30,
            "skl": 28,
            "spd": 26,
            "def": 21,
            "res": 25,
            "con": 20,
            "mov": 15,
            "lck": 30
        },
        "gender": "F",
        "movementType": "Infantry"
    },
    {
        "id": "bishop_m",
        "name": "Bishop",
        "type": "promoted",
        "baseStats": {
            "hp": 21,
            "str": 4,
            "skl": 4,
            "spd": 4,
            "def": 3,
            "res": 8,
            "con": 7,
            "mov": 6
        },
        "promotionBonus": {
            "hp": 3,
            "str": 2,
            "skl": 1,
            "spd": 0,
            "def": 3,
            "res": 2,
            "con": 1,
            "mov": 1
        },
        "promotesTo": [],
        "classAbilities": [],
        "weapons": [
            "Light",
            "Staff"
        ],
        "maxStats": {
            "hp": 60,
            "str": 25,
            "skl": 26,
            "spd": 24,
            "def": 22,
            "res": 30,
            "con": 25,
            "mov": 15,
            "lck": 30
        },
        "gender": "M",
        "movementType": "Infantry"
    },
    {
        "id": "bishop_f",
        "name": "Bishop",
        "type": "promoted",
        "baseStats": {
            "hp": 19,
            "str": 4,
            "skl": 5,
            "spd": 4,
            "def": 2,
            "res": 9,
            "con": 5,
            "mov": 6
        },
        "promotionBonus": {
            "hp": 3,
            "str": 1,
            "skl": 2,
            "spd": 1,
            "def": 2,
            "res": 2,
            "con": 1,
            "mov": 1
        },
        "promotesTo": [],
        "classAbilities": [],
        "weapons": [
            "Light",
            "Staff"
        ],
        "maxStats": {
            "hp": 60,
            "str": 25,
            "skl": 25,
            "spd": 26,
            "def": 21,
            "res": 30,
            "con": 25,
            "mov": 15,
            "lck": 30
        },
        "gender": "F",
        "movementType": "Infantry"
    },
    {
        "id": "druid_m",
        "name": "Druid",
        "type": "promoted",
        "baseStats": {
            "hp": 19,
            "str": 6,
            "skl": 3,
            "spd": 4,
            "def": 4,
            "res": 6,
            "con": 8,
            "mov": 6
        },
        "promotionBonus": {
            "hp": 4,
            "str": 0,
            "skl": 0,
            "spd": 3,
            "def": 2,
            "res": 2,
            "con": 1,
            "mov": 1
        },
        "promotesTo": [],
        "classAbilities": [],
        "weapons": [
            "Dark",
            "Staff"
        ],
        "maxStats": {
            "hp": 60,
            "str": 29,
            "skl": 26,
            "spd": 26,
            "def": 21,
            "res": 28,
            "con": 20,
            "mov": 15,
            "lck": 30
        },
        "gender": "M",
        "movementType": "Infantry"
    },
    {
        "id": "druid_f",
        "name": "Druid",
        "type": "promoted",
        "baseStats": {
            "hp": 17,
            "str": 7,
            "skl": 3,
            "spd": 4,
            "def": 3,
            "res": 7,
            "con": 4,
            "mov": 6
        },
        "promotionBonus": {
            "hp": 4,
            "str": 0,
            "skl": 0,
            "spd": 3,
            "def": 2,
            "res": 2,
            "con": 1,
            "mov": 1
        },
        "promotesTo": [],
        "classAbilities": [],
        "weapons": [
            "Dark",
            "Anima",
            "Staff"
        ],
        "maxStats": {
            "hp": 60,
            "str": 29,
            "skl": 26,
            "spd": 26,
            "def": 20,
            "res": 29,
            "con": 20,
            "mov": 15,
            "lck": 30
        },
        "gender": "F",
        "movementType": "Infantry"
    },
    {
        "id": "valkyrie",
        "name": "Valkyrie",
        "type": "promoted",
        "baseStats": {
            "hp": 19,
            "str": 4,
            "skl": 3,
            "spd": 5,
            "def": 4,
            "res": 8,
            "con": 6,
            "mov": 8
        },
        "promotionBonus": {
            "hp": 3,
            "str": 2,
            "skl": 1,
            "spd": 0,
            "def": 2,
            "res": 3,
            "con": 1,
            "mov": 1
        },
        "promotesTo": [],
        "classAbilities": [
            "Canto"
        ],
        "weapons": [
            "Anima",
            "Staff"
        ],
        "maxStats": {
            "hp": 60,
            "str": 25,
            "skl": 24,
            "spd": 25,
            "def": 24,
            "res": 28,
            "con": 25,
            "mov": 15,
            "lck": 30
        },
        "gender": "F",
        "movementType": "Cavalry"
    },
    {
        "id": "archsage",
        "name": "Archsage",
        "type": "promoted",
        "baseStats": {
            "hp": 40,
            "str": 30,
            "skl": 24,
            "spd": 20,
            "def": 20,
            "res": 28,
            "con": 9,
            "mov": 6
        },
        "promotionBonus": {},
        "promotesTo": [],
        "classAbilities": [],
        "weapons": [
            "Anima",
            "Light",
            "Dark",
            "Staff"
        ],
        "maxStats": {
            "hp": 60,
            "str": 30,
            "skl": 30,
            "spd": 25,
            "def": 20,
            "res": 30,
            "con": 20,
            "mov": 15,
            "lck": 30
        },
        "gender": "M",
        "movementType": "Infantry"
    },
    {
        "id": "dark_druid",
        "name": "Dark Druid",
        "type": "promoted",
        "baseStats": {
            "hp": 75,
            "str": 30,
            "skl": 18,
            "spd": 15,
            "def": 28,
            "res": 30,
            "con": 10,
            "mov": 6
        },
        "promotionBonus": {},
        "promotesTo": [],
        "classAbilities": [],
        "weapons": [
            "Dark",
            "Staff"
        ],
        "maxStats": {
            "hp": 60,
            "str": 30,
            "skl": 28,
            "spd": 26,
            "def": 30,
            "res": 30,
            "con": 25,
            "mov": 15,
            "lck": 30
        },
        "gender": "M",
        "movementType": "Infantry"
    },
    {
        "id": "magic_seal",
        "name": "Magic Seal",
        "type": "unpromoted",
        "baseStats": {
            "hp": 50,
            "str": 0,
            "skl": 0,
            "spd": 24,
            "def": 13,
            "res": 0,
            "con": 7,
            "mov": 6
        },
        "promotionBonus": {},
        "promotesTo": [],
        "classAbilities": [],
        "weapons": [],
        "maxStats": {
            "hp": 60,
            "str": 20,
            "skl": 20,
            "spd": 20,
            "def": 20,
            "res": 20,
            "con": 20,
            "mov": 15,
            "lck": 30
        },
        "gender": "M",
        "movementType": "Infantry"
    },
    {
        "id": "bramimond",
        "name": "Bramimond",
        "type": "unpromoted",
        "baseStats": {
            "hp": 35,
            "str": 30,
            "skl": 25,
            "spd": 19,
            "def": 18,
            "res": 30,
            "con": 6,
            "mov": 5
        },
        "promotionBonus": {},
        "promotesTo": [],
        "classAbilities": [
            "+15 Crit"
        ],
        "weapons": [
            "Bow"
        ],
        "maxStats": {
            "hp": 60,
            "str": 20,
            "skl": 20,
            "spd": 20,
            "def": 20,
            "res": 20,
            "con": 20,
            "mov": 15,
            "lck": 30
        },
        "gender": "M",
        "movementType": "Infantry"
    },
    {
        "id": "fire_dragon",
        "name": "Fire Dragon",
        "type": "unpromoted",
        "baseStats": {
            "hp": 120,
            "str": 17,
            "skl": 25,
            "spd": 15,
            "def": 20,
            "res": 20,
            "con": 25,
            "mov": 8
        },
        "promotionBonus": {},
        "promotesTo": [],
        "classAbilities": [],
        "weapons": [
            "Dragonstone"
        ],
        "maxStats": {
            "hp": 60,
            "str": 20,
            "skl": 20,
            "spd": 20,
            "def": 20,
            "res": 20,
            "con": 20,
            "mov": 15,
            "lck": 30
        },
        "gender": "M",
        "movementType": "Dragon"
    },
    {
        "id": "transporter_tent",
        "name": "Transporter (Tent)",
        "type": "unpromoted",
        "baseStats": {
            "hp": 15,
            "str": 0,
            "skl": 3,
            "spd": 3,
            "def": 3,
            "res": 0,
            "con": 25,
            "mov": 0
        },
        "promotionBonus": {},
        "promotesTo": [],
        "classAbilities": [],
        "weapons": [],
        "maxStats": {
            "hp": 60,
            "str": 20,
            "skl": 20,
            "spd": 20,
            "def": 20,
            "res": 20,
            "con": 20,
            "mov": 15,
            "lck": 30
        },
        "gender": "M",
        "movementType": "Infantry"
    },
    {
        "id": "transporter_wagon",
        "name": "Transporter (Wagon)",
        "type": "promoted",
        "baseStats": {
            "hp": 15,
            "str": 0,
            "skl": 3,
            "spd": 3,
            "def": 3,
            "res": 0,
            "con": 25,
            "mov": 5
        },
        "promotionBonus": {},
        "promotesTo": [],
        "classAbilities": [],
        "weapons": [],
        "maxStats": {
            "hp": 60,
            "str": 30,
            "skl": 30,
            "spd": 30,
            "def": 30,
            "res": 30,
            "con": 25,
            "mov": 15,
            "lck": 30
        },
        "gender": "M",
        "movementType": "Infantry"
    },
    {
        "id": "assassin",
        "name": "Assassin",
        "type": "promoted",
        "baseStats": {
            "hp": 20,
            "str": 5,
            "skl": 8,
            "spd": 12,
            "def": 6,
            "res": 2,
            "con": 7,
            "mov": 6
        },
        "promotionBonus": {
            "hp": 4,
            "str": 2,
            "skl": 3,
            "spd": 3,
            "def": 2,
            "res": 1,
            "con": 1,
            "mov": 0
        },
        "promotesTo": [],
        "classAbilities": [
            "Silencer",
            "Lockpick",
            "Steal"
        ],
        "weapons": [
            "Swords"
        ],
        "maxStats": {
            "hp": 60,
            "str": 25,
            "skl": 30,
            "spd": 30,
            "def": 25,
            "res": 20,
            "con": 20,
            "mov": 15,
            "lck": 30
        },
        "gender": "M",
        "movementType": "Infantry"
    }
]
